{
  "db_name": "PostgreSQL",
  "query": "SELECT * FROM users WHERE steam_id = $1",
  "describe": {
    "columns": [
      {
        "ordinal": 0,
        "name": "id",
        "type_info": "Uuid"
      },
      {
        "ordinal": 1,
        "name": "steam_id",
        "type_info": "Varchar"
      },
      {
        "ordinal": 2,
        "name": "username",
        "type_info": "Varchar"
      },
      {
        "ordinal": 3,
        "name": "pf_url",
        "type_info": "Text"
      },
      {
        "ordinal": 4,
        "name": "avatar",
        "type_info": "Text"
      },
      {
        "ordinal": 5,
        "name": "persona_state",
        "type_info": "Int4"
      },
      {
        "ordinal": 6,
        "name": "visibility",
        "type_info": "Int4"
      },
      {
        "ordinal": 7,
        "name": "steam_created_at",
        "type_info": "Timestamptz"
      },
      {
        "ordinal": 8,
        "name": "current_game",
        "type_info": "Varchar"
      },
      {
        "ordinal": 9,
        "name": "country",
        "type_info": "Varchar"
      },
      {
        "ordinal": 10,
        "name": "created_at",
        "type_info": "Timestamptz"
      },
      {
        "ordinal": 11,
        "name": "updated_at",
        "type_info": "Timestamptz"
      }
    ],
    "parameters": {
      "Left": [
        "Text"
      ]
    },
    "nullable": [
      false,
      false,
      false,
      false,
      false,
      false,
      false,
      false,
      true,
      true,
      false,
      false
    ]
  },
  "hash": "d12a96a649009dcd202771b18881b597450db446f66c5c7ade46a2b02f745b60"
}
